README.md
setup.cfg
setup.py
Coltext/Coltext.py
Coltext/__init__.py
Coltext.egg-info/PKG-INFO
Coltext.egg-info/SOURCES.txt
Coltext.egg-info/dependency_links.txt
Coltext.egg-info/requires.txt
Coltext.egg-info/top_level.txt