Metadata-Version: 2.1
Name: Coltext
Version: 1.0
Summary: Coltext - an alternative to colorama that can change the text color and background
Author: filcher2011
Author-email: filcher2011@mail.ru
Keywords: Coltext
Requires-Python: >=3.7
Requires-Dist: requests>=2.25.1
